litvar/__init__.py
litvar/core.py
litvar/utils.py
litvarpy-0.0.5.dist-info/LICENSE
litvarpy-0.0.5.dist-info/METADATA
litvarpy-0.0.5.dist-info/WHEEL
litvarpy-0.0.5.dist-info/top_level.txt
litvarpy-0.0.5.dist-info/RECORD
