Metadata-Version: 2.1
Name: litvarpy
Version: 0.0.5
Summary: A Python interface for LitVar on NCBI
Home-page: https://github.com/seanD111/litvarpy
Author: Sean DeLong
Author-email: sean_delong@hotmail.ca
License: "MIT",
Platform: UNKNOWN
Classifier: License :: OSI Approved :: MIT License
Classifier: Programming Language :: Python :: 3
Classifier: Programming Language :: Python :: 3.7
Requires-Python: >=3.6
License-File: LICENSE
Requires-Dist: certifi
